cognitora/__init__.py
cognitora-1.6.1.dist-info/METADATA
cognitora-1.6.1.dist-info/WHEEL
cognitora-1.6.1.dist-info/top_level.txt
cognitora-1.6.1.dist-info/RECORD
